{ "backgroundcolor":"#000000",
 "height":48,
 "infinite":false,
 "layers":[
        {
         "compression":"zlib",
         "data":"eJztmuEKwyAMhGVb3\/+VxyiDIRMTc5pE7+B+dvrJJdq6q5RyHe5TRX7yk\/9ckf\/2K5g1sozz5X8Gs0aWcZh\/8mfgt\/aIlrLwz9Ku\/NJ9Bcnvsfe1JN1XkPwr9j70eu2af6nIT\/6M\/Kg+kJUfJfKTX8LveZbRzksjKf+K93iP9YyUf\/R6ShSJ30Or+WflebRWet8\/0ZqdZ60+7I+GT6gL8u\/Fr63hX37tvbjnnQdKNf\/os1Z7ZQ3Jn\/E\/GGj+KJLW1678Umn4\/92d1vzR+ltPGn5Lv4uajej81gz1chidv54fup4y8fd6jfX3e\/3Lyj9yJpSOOfoOizzDRbRk3b3nSNO0n99bPAwj",
         "encoding":"base64",
         "height":48,
         "name":"background",
         "opacity":1,
         "type":"tilelayer",
         "visible":true,
         "width":64,
         "x":0,
         "y":0
        }, 
        {
         "draworder":"topdown",
         "name":"Object Layer 2",
         "objects":[],
         "opacity":1,
         "type":"objectgroup",
         "visible":true,
         "x":0,
         "y":0
        }, 
        {
         "draworder":"topdown",
         "name":"Object Layer 1",
         "objects":[
                {
                 "height":32,
                 "id":1,
                 "name":"player",
                 "rotation":0,
                 "type":"player",
                 "visible":true,
                 "width":32,
                 "x":96,
                 "y":480
                }, 
                {
                 "height":32,
                 "id":2,
                 "name":"monster",
                 "properties":
                    {
                     "maxdx":"10",
                     "right":"true"
                    },
                 "propertytypes":
                    {
                     "maxdx":"string",
                     "right":"string"
                    },
                 "rotation":0,
                 "type":"monster",
                 "visible":true,
                 "width":32,
                 "x":64,
                 "y":192
                }, 
                {
                 "height":32,
                 "id":3,
                 "name":"monster",
                 "properties":
                    {
                     "left":"true",
                     "maxdx":"4"
                    },
                 "propertytypes":
                    {
                     "left":"string",
                     "maxdx":"string"
                    },
                 "rotation":0,
                 "type":"monster",
                 "visible":true,
                 "width":32,
                 "x":1120,
                 "y":416
                }, 
                {
                 "height":32,
                 "id":4,
                 "name":"monster",
                 "properties":
                    {
                     "left":"true",
                     "maxdx":"4"
                    },
                 "propertytypes":
                    {
                     "left":"string",
                     "maxdx":"string"
                    },
                 "rotation":0,
                 "type":"monster",
                 "visible":true,
                 "width":32,
                 "x":1632,
                 "y":832
                }, 
                {
                 "height":32,
                 "id":5,
                 "name":"monster",
                 "properties":
                    {
                     "maxdx":"6",
                     "right":"true"
                    },
                 "propertytypes":
                    {
                     "maxdx":"string",
                     "right":"string"
                    },
                 "rotation":0,
                 "type":"monster",
                 "visible":true,
                 "width":32,
                 "x":1056,
                 "y":1312
                }, 
                {
                 "height":32,
                 "id":6,
                 "name":"monster",
                 "properties":
                    {
                     "left":"true",
                     "maxdx":"4"
                    },
                 "propertytypes":
                    {
                     "left":"string",
                     "maxdx":"string"
                    },
                 "rotation":0,
                 "type":"monster",
                 "visible":true,
                 "width":32,
                 "x":640,
                 "y":992
                }, 
                {
                 "height":32,
                 "id":7,
                 "name":"treasure",
                 "rotation":0,
                 "type":"treasure",
                 "visible":true,
                 "width":32,
                 "x":192,
                 "y":864
                }, 
                {
                 "height":32,
                 "id":8,
                 "name":"treasure",
                 "rotation":0,
                 "type":"treasure",
                 "visible":true,
                 "width":32,
                 "x":96,
                 "y":1312
                }, 
                {
                 "height":32,
                 "id":9,
                 "name":"treasure",
                 "rotation":0,
                 "type":"treasure",
                 "visible":true,
                 "width":32,
                 "x":1856,
                 "y":384
                }, 
                {
                 "height":32,
                 "id":10,
                 "name":"treasure",
                 "rotation":0,
                 "type":"treasure",
                 "visible":true,
                 "width":32,
                 "x":704,
                 "y":416
                }, 
                {
                 "height":32,
                 "id":11,
                 "name":"treasure",
                 "rotation":0,
                 "type":"treasure",
                 "visible":true,
                 "width":32,
                 "x":1984,
                 "y":192
                }, 
                {
                 "height":32,
                 "id":12,
                 "name":"treasure",
                 "rotation":0,
                 "type":"treasure",
                 "visible":true,
                 "width":32,
                 "x":608,
                 "y":1152
                }, 
                {
                 "height":32,
                 "id":13,
                 "name":"monster",
                 "properties":
                    {
                     "maxdx":"10",
                     "right":"true"
                    },
                 "propertytypes":
                    {
                     "maxdx":"string",
                     "right":"string"
                    },
                 "rotation":0,
                 "type":"monster",
                 "visible":true,
                 "width":32,
                 "x":1216,
                 "y":736
                }, 
                {
                 "height":32,
                 "id":14,
                 "name":"monster",
                 "properties":
                    {
                     "maxdx":"10",
                     "right":"true"
                    },
                 "propertytypes":
                    {
                     "maxdx":"string",
                     "right":"string"
                    },
                 "rotation":0,
                 "type":"monster",
                 "visible":true,
                 "width":32,
                 "x":1856,
                 "y":1344
                }, 
                {
                 "height":32,
                 "id":15,
                 "name":"monster",
                 "properties":
                    {
                     "left":"true",
                     "maxdx":"4"
                    },
                 "propertytypes":
                    {
                     "left":"string",
                     "maxdx":"string"
                    },
                 "rotation":0,
                 "type":"monster",
                 "visible":true,
                 "width":32,
                 "x":1024,
                 "y":192
                }, 
                {
                 "height":32,
                 "id":16,
                 "name":"treasure",
                 "rotation":0,
                 "type":"treasure",
                 "visible":true,
                 "width":32,
                 "x":32,
                 "y":192
                }, 
                {
                 "height":32,
                 "id":17,
                 "name":"treasure",
                 "rotation":0,
                 "type":"treasure",
                 "visible":true,
                 "width":32,
                 "x":1984,
                 "y":1344
                }],
         "opacity":1,
         "type":"objectgroup",
         "visible":true,
         "x":0,
         "y":0
        }],
 "nextobjectid":18,
 "orientation":"orthogonal",
 "renderorder":"right-down",
 "tiledversion":"1.1.6",
 "tileheight":32,
 "tilesets":[
        {
         "columns":5,
         "firstgid":1,
         "image":"jsproject-test\/tiles.png",
         "imageheight":32,
         "imagewidth":160,
         "margin":0,
         "name":"tiles",
         "spacing":0,
         "tilecount":5,
         "tileheight":32,
         "tilewidth":32
        }],
 "tilewidth":32,
 "type":"map",
 "version":1,
 "width":64
}